neighborhoods/__init__.py
neighborhoods/neighborhoods.py
neighborhoods/data/ZillowNeighborhoods-AK.dbf
neighborhoods/data/ZillowNeighborhoods-AK.prj
neighborhoods/data/ZillowNeighborhoods-AK.shp
neighborhoods/data/ZillowNeighborhoods-AK.shp.xml
neighborhoods/data/ZillowNeighborhoods-AK.shx
neighborhoods/data/ZillowNeighborhoods-AL.dbf
neighborhoods/data/ZillowNeighborhoods-AL.prj
neighborhoods/data/ZillowNeighborhoods-AL.shp
neighborhoods/data/ZillowNeighborhoods-AL.shp.xml
neighborhoods/data/ZillowNeighborhoods-AL.shx
neighborhoods/data/ZillowNeighborhoods-AR.dbf
neighborhoods/data/ZillowNeighborhoods-AR.prj
neighborhoods/data/ZillowNeighborhoods-AR.shp
neighborhoods/data/ZillowNeighborhoods-AR.shp.xml
neighborhoods/data/ZillowNeighborhoods-AR.shx
neighborhoods/data/ZillowNeighborhoods-AZ.dbf
neighborhoods/data/ZillowNeighborhoods-AZ.prj
neighborhoods/data/ZillowNeighborhoods-AZ.shp
neighborhoods/data/ZillowNeighborhoods-AZ.shp.xml
neighborhoods/data/ZillowNeighborhoods-AZ.shx
neighborhoods/data/ZillowNeighborhoods-CA.dbf
neighborhoods/data/ZillowNeighborhoods-CA.prj
neighborhoods/data/ZillowNeighborhoods-CA.shp
neighborhoods/data/ZillowNeighborhoods-CA.shp.xml
neighborhoods/data/ZillowNeighborhoods-CA.shx
neighborhoods/data/ZillowNeighborhoods-CO.dbf
neighborhoods/data/ZillowNeighborhoods-CO.prj
neighborhoods/data/ZillowNeighborhoods-CO.shp
neighborhoods/data/ZillowNeighborhoods-CO.shp.xml
neighborhoods/data/ZillowNeighborhoods-CO.shx
neighborhoods/data/ZillowNeighborhoods-CT.dbf
neighborhoods/data/ZillowNeighborhoods-CT.prj
neighborhoods/data/ZillowNeighborhoods-CT.shp
neighborhoods/data/ZillowNeighborhoods-CT.shp.xml
neighborhoods/data/ZillowNeighborhoods-CT.shx
neighborhoods/data/ZillowNeighborhoods-DC.dbf
neighborhoods/data/ZillowNeighborhoods-DC.prj
neighborhoods/data/ZillowNeighborhoods-DC.shp
neighborhoods/data/ZillowNeighborhoods-DC.shp.xml
neighborhoods/data/ZillowNeighborhoods-DC.shx
neighborhoods-0.5.dist-info/DESCRIPTION.rst
neighborhoods-0.5.dist-info/METADATA
neighborhoods-0.5.dist-info/metadata.json
neighborhoods-0.5.dist-info/RECORD
neighborhoods-0.5.dist-info/top_level.txt
neighborhoods-0.5.dist-info/WHEEL
