Metadata-Version: 2.0
Name: neighborhoods
Version: 0.5
Summary: Lon/lat to Neighborhood for Humans
Home-page: https://github.com/styleseat/latlong-to-neighborhood
Author: StyleSeat, Inc.
Author-email: dev@styleseat.com
License: Apache 2.0
Keywords: neighborhoods geospatial geo
Platform: UNKNOWN
Classifier: Development Status :: 1 - Planning
Classifier: Intended Audience :: Developers
Classifier: Natural Language :: English
Classifier: Topic :: Scientific/Engineering :: GIS
Classifier: Topic :: Utilities
Classifier: Programming Language :: Python :: 2.7
Classifier: License :: OSI Approved :: Apache Software License
Requires-Dist: Fiona
Requires-Dist: Shapely
